fqdn/__init__.py
fqdn/_compat.py
fqdn-1.5.1.dist-info/LICENSE
fqdn-1.5.1.dist-info/METADATA
fqdn-1.5.1.dist-info/WHEEL
fqdn-1.5.1.dist-info/top_level.txt
fqdn-1.5.1.dist-info/zip-safe
fqdn-1.5.1.dist-info/RECORD
